pyvsphere/__init__.py
pyvsphere/mymodule.py
pyvsphere/vcenter.py
pyvsphere/vmware_datastore_facts.py
pyvsphere/vmware_guest_disk_info.py
pyvsphere/vmware_guest_facts.py
pyvsphere/vmware_host_facts.py
pyvsphere/vmware_portgroup_facts.py
pyvsphere/vmware_resource_pool_facts.py
pyvsphere/vmware_vm_facts.py
pyvsphere/vmware_vswitch_facts.py
pyvsphere/vsphere.py
pyvsphere-0.0.7.dist-info/METADATA
pyvsphere-0.0.7.dist-info/WHEEL
pyvsphere-0.0.7.dist-info/top_level.txt
pyvsphere-0.0.7.dist-info/RECORD
