Metadata-Version: 2.1
Name: pyvsphere
Version: 0.0.7
Summary: Vsphere SDK package
Home-page: https://github.com/Maliaotw/pyvsphere.git
Author: Maliao
Author-email: maliaotw@gmail.com
License: UNKNOWN
Platform: UNKNOWN
Classifier: Programming Language :: Python :: 3
Classifier: License :: OSI Approved :: MIT License
Classifier: Operating System :: OS Independent
Requires-Python: >=3.6
Requires-Dist: ansible (==2.9.2)
Requires-Dist: pyvmomi
